ros_std_msgs-5.5.1.data/data/include/std_msgs/std_msgs/msg/bool.h
ros_std_msgs-5.5.1.data/data/include/std_msgs/std_msgs/msg/bool.hpp
ros_std_msgs-5.5.1.data/data/include/std_msgs/std_msgs/msg/byte.h
ros_std_msgs-5.5.1.data/data/include/std_msgs/std_msgs/msg/byte.hpp
ros_std_msgs-5.5.1.data/data/include/std_msgs/std_msgs/msg/byte_multi_array.h
ros_std_msgs-5.5.1.data/data/include/std_msgs/std_msgs/msg/byte_multi_array.hpp
ros_std_msgs-5.5.1.data/data/include/std_msgs/std_msgs/msg/char.h
ros_std_msgs-5.5.1.data/data/include/std_msgs/std_msgs/msg/char.hpp
ros_std_msgs-5.5.1.data/data/include/std_msgs/std_msgs/msg/color_rgba.h
ros_std_msgs-5.5.1.data/data/include/std_msgs/std_msgs/msg/color_rgba.hpp
ros_std_msgs-5.5.1.data/data/include/std_msgs/std_msgs/msg/empty.h
ros_std_msgs-5.5.1.data/data/include/std_msgs/std_msgs/msg/empty.hpp
ros_std_msgs-5.5.1.data/data/include/std_msgs/std_msgs/msg/float32.h
ros_std_msgs-5.5.1.data/data/include/std_msgs/std_msgs/msg/float32.hpp
ros_std_msgs-5.5.1.data/data/include/std_msgs/std_msgs/msg/float32_multi_array.h
ros_std_msgs-5.5.1.data/data/include/std_msgs/std_msgs/msg/float32_multi_array.hpp
ros_std_msgs-5.5.1.data/data/include/std_msgs/std_msgs/msg/float64.h
ros_std_msgs-5.5.1.data/data/include/std_msgs/std_msgs/msg/float64.hpp
ros_std_msgs-5.5.1.data/data/include/std_msgs/std_msgs/msg/float64_multi_array.h
ros_std_msgs-5.5.1.data/data/include/std_msgs/std_msgs/msg/float64_multi_array.hpp
ros_std_msgs-5.5.1.data/data/include/std_msgs/std_msgs/msg/header.h
ros_std_msgs-5.5.1.data/data/include/std_msgs/std_msgs/msg/header.hpp
ros_std_msgs-5.5.1.data/data/include/std_msgs/std_msgs/msg/int16.h
ros_std_msgs-5.5.1.data/data/include/std_msgs/std_msgs/msg/int16.hpp
ros_std_msgs-5.5.1.data/data/include/std_msgs/std_msgs/msg/int16_multi_array.h
ros_std_msgs-5.5.1.data/data/include/std_msgs/std_msgs/msg/int16_multi_array.hpp
ros_std_msgs-5.5.1.data/data/include/std_msgs/std_msgs/msg/int32.h
ros_std_msgs-5.5.1.data/data/lib/python3.13/site-packages/std_msgs-5.5.1-py3.13.egg-info/PKG-INFO
ros_std_msgs-5.5.1.data/data/lib/python3.13/site-packages/std_msgs-5.5.1-py3.13.egg-info/SOURCES.txt
ros_std_msgs-5.5.1.data/data/lib/python3.13/site-packages/std_msgs-5.5.1-py3.13.egg-info/dependency_links.txt
ros_std_msgs-5.5.1.data/data/lib/python3.13/site-packages/std_msgs-5.5.1-py3.13.egg-info/top_level.txt
ros_std_msgs-5.5.1.dist-info/METADATA
ros_std_msgs-5.5.1.dist-info/WHEEL
ros_std_msgs-5.5.1.dist-info/top_level.txt
ros_std_msgs-5.5.1.dist-info/RECORD
ros_std_msgs-5.5.1.dist-info/licenses/LICENSE
