Metadata-Version: 2.4
Name: ros-std-msgs
Version: 5.5.1
Summary: The ROS `std_msgs` package offers standard and primitive message types, including integers, floats, strings, and arrays, for fundamental data exchange.
License-File: LICENSE
Requires-Dist: ros-builtin-interfaces~=2.3.0
Requires-Dist: ros-rosidl-default-runtime~=1.7.1
Dynamic: description
Dynamic: description-content-type
Dynamic: license-file
Dynamic: requires-dist
Dynamic: summary
